beet_observer/__init__.py
beet_observer/data_pack.py
beet_observer/plugin.py
beet_observer/resource_pack.py
beet_observer-0.7.3.dist-info/LICENSE
beet_observer-0.7.3.dist-info/METADATA
beet_observer-0.7.3.dist-info/WHEEL
beet_observer-0.7.3.dist-info/RECORD
