Metadata-Version: 2.1
Name: beet-observer
Version: 0.7.3
Summary: A beet plugin to automatically generate overlays from previous datapacks
License: MIT
Author: BPR02
Author-email: dev@bpr02.com
Requires-Python: >=3.10,<4.0
Classifier: License :: OSI Approved :: MIT License
Classifier: Programming Language :: Python :: 3
Classifier: Programming Language :: Python :: 3.10
Classifier: Programming Language :: Python :: 3.11
Classifier: Programming Language :: Python :: 3.12
Requires-Dist: beet (>=0.108.5)
Requires-Dist: pillow (>=11.0.0,<12.0.0)
